{
    "products": [
        {
            "id" : 0,
            "title" : "아웃백 상품권 5만원권 11%",
            "hit" : 1,
            "price" : "25000~",
            "shipping" : "무료배송",
            "description" : "테스트 상품입니다.",
            "thumbnail" : "http://gdimg.gmarket.co.kr/1969140335/still/280?ver=1611212191",
            "link": "http://click.linkprice.com/click.php?m=gmarket&a=A100664688&l=9999&l_cd1=3&l_cd2=q&tu=http%3A%2F%2Fitem.gmarket.co.kr%2FDetailView%2FItem.asp%3FgoodsCode%3D1969140335",
            "origin": "쿨앤조이",
            "shop": "지마켓"
        },
        {
            "id" : 1,
            "title" : "아웃백 상품권 5만원권 11%할인한다는데 한번 보세요",
            "hit" : 1,
            "price" : "25000~",
            "shipping" : "무료배송",
            "description" : "테스트 상품입니다.테스트 상품입니다.테스트 상품입니다.테스트 상품입니다.테스트 상품입니다.테스트 상품입니다.테스트 상품입니다.테스트 상품입니다.테스트 상품입니다.테스트 상품입니다.테스트 상품입니다.테스트 상품입니다.테스트 상품입니다.",
            "thumbnail" : "http://gdimg.gmarket.co.kr/1969140335/still/280?ver=1611212191",
            "link": "http://click.linkprice.com/click.php?m=gmarket&a=A100664688&l=9999&l_cd1=3&l_cd2=q&tu=http%3A%2F%2Fitem.gmarket.co.kr%2FDetailView%2FItem.asp%3FgoodsCode%3D1969140335",
            "origin": "쿨앤조이",
            "shop": "지마켓"
        },
        {
            "id" : 1,
            "title" : "아웃백 상품권 5만원권 11%",
            "hit" : 1,
            "price" : "25000~",
            "shipping" : "무료배송",
            "description" : "테스트 상품입니다.",
            "thumbnail" : "http://gdimg.gmarket.co.kr/1969140335/still/280?ver=1611212191",
            "link": "http://click.linkprice.com/click.php?m=gmarket&a=A100664688&l=9999&l_cd1=3&l_cd2=q&tu=http%3A%2F%2Fitem.gmarket.co.kr%2FDetailView%2FItem.asp%3FgoodsCode%3D1969140335",
            "origin": "쿨앤조이",
            "shop": "지마켓"
        },
        {
            "id" : 1,
            "title" : "아웃백 상품권 5만원권 11%",
            "hit" : 1,
            "price" : "25000~",
            "shipping" : "무료배송",
            "description" : "테스트 상품입니다.",
            "thumbnail" : "http://gdimg.gmarket.co.kr/1969140335/still/280?ver=1611212191",
            "link": "http://click.linkprice.com/click.php?m=gmarket&a=A100664688&l=9999&l_cd1=3&l_cd2=q&tu=http%3A%2F%2Fitem.gmarket.co.kr%2FDetailView%2FItem.asp%3FgoodsCode%3D1969140335",
            "origin": "쿨앤조이",
            "shop": "지마켓"
        },
        {
            "id" : 1,
            "title" : "아웃백 상품권 5만원권 11%",
            "hit" : 1,
            "price" : "25000~",
            "shipping" : "무료배송",
            "description" : "테스트 상품입니다.",
            "thumbnail" : "http://gdimg.gmarket.co.kr/1969140335/still/280?ver=1611212191",
            "link": "http://click.linkprice.com/click.php?m=gmarket&a=A100664688&l=9999&l_cd1=3&l_cd2=q&tu=http%3A%2F%2Fitem.gmarket.co.kr%2FDetailView%2FItem.asp%3FgoodsCode%3D1969140335",
            "origin": "쿨앤조이",
            "shop": "지마켓"
        },
        {
            "id" : 1,
            "title" : "아웃백 상품권 5만원권 11%",
            "hit" : 1,
            "price" : "25000~",
            "shipping" : "무료배송",
            "description" : "테스트 상품입니다.",
            "thumbnail" : "http://gdimg.gmarket.co.kr/1969140335/still/280?ver=1611212191",
            "link": "http://click.linkprice.com/click.php?m=gmarket&a=A100664688&l=9999&l_cd1=3&l_cd2=q&tu=http%3A%2F%2Fitem.gmarket.co.kr%2FDetailView%2FItem.asp%3FgoodsCode%3D1969140335",
            "origin": "쿨앤조이",
            "shop": "지마켓"
        },
        {
            "id" : 1,
            "title" : "아웃백 상품권 5만원권 11%",
            "hit" : 1,
            "price" : "25000~",
            "shipping" : "무료배송",
            "description" : "테스트 상품입니다.",
            "thumbnail" : "http://gdimg.gmarket.co.kr/1969140335/still/280?ver=1611212191",
            "link": "http://click.linkprice.com/click.php?m=gmarket&a=A100664688&l=9999&l_cd1=3&l_cd2=q&tu=http%3A%2F%2Fitem.gmarket.co.kr%2FDetailView%2FItem.asp%3FgoodsCode%3D1969140335",
            "origin": "쿨앤조이",
            "shop": "지마켓"
        },
        {
            "id" : 1,
            "title" : "아웃백 상품권 5만원권 11%",
            "hit" : 1,
            "price" : "25000~",
            "shipping" : "무료배송",
            "description" : "테스트 상품입니다.",
            "thumbnail" : "http://gdimg.gmarket.co.kr/1969140335/still/280?ver=1611212191",
            "link": "http://click.linkprice.com/click.php?m=gmarket&a=A100664688&l=9999&l_cd1=3&l_cd2=q&tu=http%3A%2F%2Fitem.gmarket.co.kr%2FDetailView%2FItem.asp%3FgoodsCode%3D1969140335",
            "origin": "쿨앤조이",
            "shop": "지마켓"
        },
        {
            "id" : 1,
            "title" : "아웃백 상품권 5만원권 11%",
            "hit" : 1,
            "price" : "25000~",
            "shipping" : "무료배송",
            "description" : "테스트 상품입니다.",
            "thumbnail" : "http://gdimg.gmarket.co.kr/1969140335/still/280?ver=1611212191",
            "link": "http://click.linkprice.com/click.php?m=gmarket&a=A100664688&l=9999&l_cd1=3&l_cd2=q&tu=http%3A%2F%2Fitem.gmarket.co.kr%2FDetailView%2FItem.asp%3FgoodsCode%3D1969140335",
            "origin": "쿨앤조이",
            "shop": "지마켓"
        },
        {
            "id" : 1,
            "title" : "아웃백 상품권 5만원권 11%",
            "hit" : 1,
            "price" : "25000~",
            "shipping" : "무료배송",
            "description" : "테스트 상품입니다.",
            "thumbnail" : "http://gdimg.gmarket.co.kr/1969140335/still/280?ver=1611212191",
            "link": "http://click.linkprice.com/click.php?m=gmarket&a=A100664688&l=9999&l_cd1=3&l_cd2=q&tu=http%3A%2F%2Fitem.gmarket.co.kr%2FDetailView%2FItem.asp%3FgoodsCode%3D1969140335",
            "origin": "쿨앤조이",
            "shop": "지마켓"
        }
    ]
}